{
  "headline": "Celtics crush Philly while Bruins collapse and Red Sox find new life",
  "morning_brew": [
    "The C's are one win away from moving on after a 128-96 clinic in Philly. Jayson Tatum was doing it all with thirty points and eleven assists, but the real story was Payton Pritchard. The kid was unconscious from deep, hitting six threes on his way to thirty-two points. Spoiling Joel Embiid's return like that is exactly what this team needed to do. We are sitting on eighteen banners and this group looks ready to chase number nineteen.",
    "Losing 6-1 to the Sabres in a playoff game is absolutely brutal. Jeremy Swayman got hung out to dry and the bench could not even look him in the eye when he got pulled. Marco Sturm is right to call it embarrassing because that effort was non-existent. One more loss and the season is over, which would be a pathetic way to follow up forty-five wins. The energy at the Garden was sucked out early and they never recovered.",
    "Boston picked up a 5-3 win over the Orioles to start the post-Cora era. Willson Contreras stayed hot with his sixth homer of the year and the bullpen actually held a lead for the starter, Early. It was a solid response after a chaotic weekend in the front office. One win does not fix a 11-17 start, but at least they showed some life on the field. We'll see if they can keep it rolling tonight at the Rogers Centre.",
    "The draft is in the books and now the rumor mill is spinning about a trade for A.J. Brown. Reflecting on the weekend, the front office focused on protection and defense with picks like Caleb Lomu and Gabe Jacas, but adding a true number one receiver would change everything for Drake Maye. Eight wins last season was an improvement, but this city expects a return to those dynasty years. If they can pull off a move for a star receiver, the rebuild gets a massive boost."
  ],
  "trend_watch": [
    {
      "category": "Heater",
      "player": "Payton Pritchard",
      "trend": "Exploded for 32 points including six 3-pointers off the bench.",
      "dans_take": "The kid is playing out of his mind and giving this second unit exactly what they need."
    },
    {
      "category": "Cold Snap",
      "player": "Jeremy Swayman",
      "trend": "Allowed four goals in the first period and was pulled in the third.",
      "dans_take": "He had zero help from the defense but you cannot give up four in the first period of a playoff game."
    },
    {
      "category": "Heater",
      "player": "Willson Contreras",
      "trend": "Hit his sixth home run of the year and his second in as many games.",
      "dans_take": "He is the only guy in this lineup consistently doing his job right now."
    }
  ],
  "news_digest": [
    {
      "headline": "Celtics spoil Embiid's return, take 3-1 series lead",
      "url": "http://www.espn.com/nba/recap?gameId=401869406",
      "dans_take": "Putting the 76ers on the brink of elimination in their own building is a beautiful thing."
    },
    {
      "headline": "Bruins on the brink of elimination after blowout loss to Sabres",
      "url": "https://www.espn.com/nhl/story/_/id/48604001/embarrassed-bruins-brink-playoff-elimination-blowout-loss-sabres",
      "dans_take": "Sturm called it embarrassing and he is being kind because that was a total no-show."
    },
    {
      "headline": "What could the Patriots trade for receiver A.J. Brown?",
      "url": "https://www.espn.com/nfl/story/_/id/48592782/new-england-patriots-aj-brown-trade-compensation-eagles-2026-nfl-draft-recap",
      "dans_take": "If this trade actually happens, it would be the biggest move this team has made in years."
    }
  ],
  "box_scores": {
    "celtics": {
      "sport": "NBA",
      "home_team": "Philadelphia 76ers",
      "away_team": "Boston Celtics",
      "home_score": 96,
      "away_score": 128,
      "game_date": "2026-04-26",
      "played": true,
      "season_type": "playoff"
    },
    "bruins": {
      "sport": "NHL",
      "home_team": "Boston Bruins",
      "away_team": "Buffalo Sabres",
      "home_score": 1,
      "away_score": 6,
      "game_date": "2026-04-26",
      "played": true,
      "season_type": "playoff"
    },
    "redsox": {
      "sport": "MLB",
      "home_team": "Baltimore Orioles",
      "away_team": "Boston Red Sox",
      "home_score": 3,
      "away_score": 5,
      "game_date": "2026-04-26",
      "played": true,
      "season_type": "regular"
    },
    "patriots": {
      "sport": "NFL",
      "home_team": null,
      "away_team": null,
      "home_score": null,
      "away_score": null,
      "game_date": "2026-04-26",
      "played": false,
      "season_type": "offseason"
    }
  },
  "schedule": [
    {
      "date": "2026-04-27",
      "matchup": "Boston Red Sox at Toronto Blue Jays",
      "time_et": "7:07 PM ET"
    },
    {
      "date": "2026-04-28",
      "matchup": "Philadelphia 76ers at Boston Celtics",
      "time_et": "7:00 PM ET"
    },
    {
      "date": "2026-04-28",
      "matchup": "Boston Red Sox at Toronto Blue Jays",
      "time_et": "7:07 PM ET"
    },
    {
      "date": "2026-04-28",
      "matchup": "Boston Bruins at Buffalo Sabres",
      "time_et": "7:30 PM ET"
    },
    {
      "date": "2026-04-29",
      "matchup": "Boston Red Sox at Toronto Blue Jays",
      "time_et": "3:07 PM ET"
    },
    {
      "date": "2026-04-30",
      "matchup": "Boston Celtics at Philadelphia 76ers",
      "time_et": "12:00 AM ET"
    },
    {
      "date": "2026-05-01",
      "matchup": "Buffalo Sabres at Boston Bruins",
      "time_et": "12:00 PM ET"
    },
    {
      "date": "2026-05-01",
      "matchup": "Houston Astros at Boston Red Sox",
      "time_et": "7:10 PM ET"
    },
    {
      "date": "2026-05-02",
      "matchup": "Philadelphia 76ers at Boston Celtics",
      "time_et": "12:00 AM ET"
    },
    {
      "date": "2026-05-02",
      "matchup": "Houston Astros at Boston Red Sox",
      "time_et": "4:10 PM ET"
    },
    {
      "date": "2026-05-03",
      "matchup": "Boston Bruins at Buffalo Sabres",
      "time_et": "12:00 PM ET"
    },
    {
      "date": "2026-05-03",
      "matchup": "Houston Astros at Boston Red Sox",
      "time_et": "1:35 PM ET"
    },
    {
      "date": "2026-05-04",
      "matchup": "Boston Red Sox at Detroit Tigers",
      "time_et": "6:40 PM ET"
    }
  ],
  "generated_at": "2026-04-27T10:12:14.123230+00:00"
}